sankeydata/__init__.py
sankeydata/sankey_data.py
sankeydata-0.1.dev0.dist-info/DESCRIPTION.rst
sankeydata-0.1.dev0.dist-info/METADATA
sankeydata-0.1.dev0.dist-info/RECORD
sankeydata-0.1.dev0.dist-info/WHEEL
sankeydata-0.1.dev0.dist-info/metadata.json
sankeydata-0.1.dev0.dist-info/top_level.txt
