Metadata-Version: 2.0
Name: sankeydata
Version: 0.1.dev0
Summary: Data structure for Sankey diagrams.
Home-page: https://github.com/ricklupton/sankeydata
Author: Rick Lupton
Author-email: mail@ricklupton.name
License: UNKNOWN
Keywords: Sankey diagram flow data format JSON
Platform: UNKNOWN
Classifier: Development Status :: 4 - Beta
Classifier: Intended Audience :: Developers
Classifier: License :: OSI Approved :: MIT License
Classifier: Programming Language :: Python :: 3
Classifier: Programming Language :: Python :: 3.4
Classifier: Programming Language :: Python :: 3.5
Classifier: Programming Language :: Python :: 3.6
Requires-Dist: attrs
Provides-Extra: dev
Provides-Extra: test
Requires-Dist: pytest; extra == 'test'
